cli_progress/ANSIWidget.py
cli_progress/BackgroundWidget.py
cli_progress/LogListWidget.py
cli_progress/__init__.py
cli_progress/__main__.py
cli_progress/progress_ui.py
cli_progress-2.0.0.dist-info/LICENSE
cli_progress-2.0.0.dist-info/METADATA
cli_progress-2.0.0.dist-info/WHEEL
cli_progress-2.0.0.dist-info/entry_points.txt
cli_progress-2.0.0.dist-info/top_level.txt
cli_progress-2.0.0.dist-info/RECORD
