Metadata-Version: 2.1
Name: cli_progress
Version: 2.0.0
Summary: Awesome cli_progress created by hiddify
Home-page: https://github.com/hiddify/cli_progress/
Author: hiddify
License-File: LICENSE
Requires-Dist: urwid ==2.6.10
Requires-Dist: argparse ==1.4.0
Requires-Dist: asyncio
Provides-Extra: test
Requires-Dist: pytest ; extra == 'test'
Requires-Dist: coverage ; extra == 'test'
Requires-Dist: flake8 ; extra == 'test'
Requires-Dist: black ; extra == 'test'
Requires-Dist: isort ; extra == 'test'
Requires-Dist: pytest-cov ; extra == 'test'
Requires-Dist: mypy ; extra == 'test'
Requires-Dist: gitchangelog ; extra == 'test'
Requires-Dist: mkdocs ; extra == 'test'
